cetpy/__init__.py
cetpy/CaseTools/FilterFunctions.py
cetpy/CaseTools/RegressionDataSet.py
cetpy/CaseTools/_CaseGenerator.py
cetpy/CaseTools/_CaseRunner.py
cetpy/CaseTools/_DataSet.py
cetpy/CaseTools/__init__.py
cetpy/Configuration/_ConfigurationManager.py
cetpy/Configuration/_ModuleManager.py
cetpy/Configuration/_Session.py
cetpy/Configuration/__init__.py
cetpy/Configuration/default_config_parameters.toml
cetpy/Configuration/default_session_config.toml
cetpy/Modules/__init__.py
cetpy/Modules/Fluid/_FluidCoolProp.py
cetpy/Modules/Fluid/_FluidSkeleton.py
cetpy/Modules/Fluid/__init__.py
cetpy/Modules/FluidBlock/_CompressibleFluidBlock.py
cetpy/Modules/FluidBlock/_FluidBlock.py
cetpy/Modules/FluidBlock/_FluidPort.py
cetpy/Modules/FluidBlock/_GenericFluidBlock.py
cetpy/Modules/FluidBlock/__init__.py
cetpy/Modules/Material/_MaterialGiven.py
cetpy/Modules/Material/_MaterialSkeleton.py
cetpy/Modules/Material/__init__.py
cetpy/Modules/Report/_Report.py
cetpy/Modules/Report/_ReportPort.py
cetpy/Modules/Report/_ReportSolver.py
cetpy/Modules/Report/__init__.py
cetpy/Modules/Solver/_ContinuousFlowSolver.py
cetpy/Modules/Solver/_Solver.py
cetpy/Modules/Solver/__init__.py
cetpy/Modules/SysML/_Block.py
cetpy/Modules/SysML/_ContinuousPort.py
cetpy/Modules/SysML/_FlowProperty.py
cetpy/Modules/SysML/_PartProperty.py
cetpy/Modules/SysML/_Port.py
cetpy/Modules/SysML/_ProxyProperty.py
cetpy/Modules/SysML/_ValueProperty.py
cetpy/Modules/SysML/__init__.py
cetpy/Modules/Utilities/InputValidation.py
cetpy/Modules/Utilities/Labelling.py
cetpy/Modules/Utilities/__init__.py
cetpy/tests/__init__.py
cetpy/tests/TestModules/__init__.py
cetpy/tests/TestModules/TestSysML/__init__.py
cetpy/tests/TestModules/TestSysML/test_Block.py
cetpy-0.1.0.dist-info/LICENSE.txt
cetpy-0.1.0.dist-info/METADATA
cetpy-0.1.0.dist-info/WHEEL
cetpy-0.1.0.dist-info/top_level.txt
cetpy-0.1.0.dist-info/RECORD
