Metadata-Version: 2.1
Name: cetpy
Version: 0.1.0
Summary: Congruent Engineering Toolbox
Home-page: https://github.com/CongruentEngineeringToolbox/cetpy
Author: CET developers
Keywords: engineering,system engineering,congruent engineering
Classifier: Development Status :: 2 - Pre-Alpha
Classifier: Intended Audience :: Developers
Classifier: Intended Audience :: Science/Research
Classifier: Topic :: Scientific/Engineering
Classifier: License :: OSI Approved :: MIT License
Classifier: Programming Language :: Python :: 3
Classifier: Programming Language :: Python :: 3.10
Classifier: Programming Language :: Python :: 3 :: Only
Requires-Python: >=3.10, <4
License-File: LICENSE.txt
Requires-Dist: numpy
Requires-Dist: pandas
Requires-Dist: CoolProp
Requires-Dist: tomli
Requires-Dist: tabulate
Requires-Dist: smt
Requires-Dist: pytest
Requires-Dist: matplotlib
Requires-Dist: statsmodels
Requires-Dist: scikit-learn
